anvil_web3/__init__.py
anvil_web3/anvil.py
anvil_web3/rpc.py
anvil_web3/types.py
anvil_web3/wrapper.py
anvil_web3-0.0.4.dist-info/LICENSE
anvil_web3-0.0.4.dist-info/WHEEL
anvil_web3-0.0.4.dist-info/METADATA
anvil_web3-0.0.4.dist-info/RECORD
