Metadata-Version: 2.1
Name: anvil-web3
Version: 0.0.4
Summary: Wrapper and Web3 class to interact with and create Anvil chains
Author: alpinevm
Classifier: License :: OSI Approved :: MIT License
